videosdk/plugins/neuphonic/__init__.py
videosdk/plugins/neuphonic/tts.py
videosdk/plugins/neuphonic/version.py
videosdk_plugins_neuphonic-0.0.58.dist-info/METADATA
videosdk_plugins_neuphonic-0.0.58.dist-info/WHEEL
videosdk_plugins_neuphonic-0.0.58.dist-info/RECORD
