Metadata-Version: 2.4
Name: videosdk-plugins-neuphonic
Version: 0.0.58
Summary: VideoSDK Agent Framework plugin for Neuphonic AI
Author: videosdk
Keywords: ai,audio,neuphonic,tts,video,videosdk
Classifier: Development Status :: 4 - Beta
Classifier: Intended Audience :: Developers
Classifier: Topic :: Communications :: Conferencing
Classifier: Topic :: Multimedia :: Sound/Audio
Classifier: Topic :: Multimedia :: Video
Classifier: Topic :: Scientific/Engineering :: Artificial Intelligence
Requires-Python: >=3.11
Requires-Dist: aiohttp>=3.9.0
Requires-Dist: videosdk-agents>=0.0.58
